[
  {
    "x" : 71.07797241210938,
    "y" : -13.66384887695312,
    "type" : "Point"
  },
  {
    "x" : 48.66818237304688,
    "y" : 13.93441772460938,
    "type" : "Point"
  },
  {
    "x" : 19.41778564453125,
    "y" : 35.34561157226562,
    "type" : "Point"
  },
  {
    "x" : -14.04400634765625,
    "y" : 41.21307373046875,
    "type" : "Point"
  },
  {
    "x" : -46.1650390625,
    "y" : 32.53482055664062,
    "type" : "Point"
  },
  {
    "x" : -68.76138305664062,
    "y" : 13.80892944335938,
    "type" : "Point"
  },
  {
    "x" : -78.97659301757812,
    "y" : -8.10260009765625,
    "type" : "Point"
  },
  {
    "x" : -81.659912109375,
    "y" : -31.86349487304688,
    "type" : "Point"
  },
  {
    "x" : -77.81967163085938,
    "y" : -53.78115844726562,
    "type" : "Point"
  },
  {
    "x" : -69.11569213867188,
    "y" : -76.7059326171875,
    "type" : "Point"
  },
  {
    "x" : -50.54458618164062,
    "y" : -94.27365112304688,
    "type" : "Point"
  },
  {
    "x" : -19.45965576171875,
    "y" : -102.1513137817383,
    "type" : "Point"
  },
  {
    "x" : 4.4635009765625,
    "y" : -99.49578857421875,
    "type" : "Point"
  },
  {
    "x" : 32.2381591796875,
    "y" : -87.455322265625,
    "type" : "Point"
  },
  {
    "x" : 48.96243286132812,
    "y" : -63.0634765625,
    "type" : "Point"
  },
  {
    "x" : 62.20101928710938,
    "y" : -27.075927734375,
    "type" : "Point"
  }
]